aiml_api/__init__.py
aiml_api/config.py
aiml_api/main.py
aiml_api-0.1.4.dist-info/LICENSE
aiml_api-0.1.4.dist-info/METADATA
aiml_api-0.1.4.dist-info/WHEEL
aiml_api-0.1.4.dist-info/top_level.txt
aiml_api-0.1.4.dist-info/RECORD
