Metadata-Version: 2.2
Name: aiml_api
Version: 0.1.4
Summary: AI/ML API library for a simple and seamless connection to AI/ML services.
Requires-Python: >=3.12
License-File: LICENSE
Requires-Dist: openai>=1.55.1
Requires-Dist: pydantic-settings>=2.7.1
